{
  "ID": "7bc35a3b-0e63-402b-8a65-8e759ffd0cf6",
  "Version": "2.3.4",
  "Name": "DN_qiangzhuang01",
  "Content": {
    "Content": {
      "Animation": {
        "Duration": 100,
        "Speed": 1.0,
        "Timelines": [
          {
            "ActionTag": -106618142,
            "Property": "Position",
            "Frames": [
              {
                "X": 0.0,
                "Y": 0.0,
                "FrameIndex": 0,
                "EasingData": {
                  "Type": 0
                },
                "ctype": "PointFrameData"
              },
              {
                "X": 0.0,
                "Y": 0.0,
                "FrameIndex": 7,
                "EasingData": {
                  "Type": 0
                },
                "ctype": "PointFrameData"
              },
              {
                "X": 0.0,
                "Y": 0.0,
                "FrameIndex": 14,
                "EasingData": {
                  "Type": 0
                },
                "ctype": "PointFrameData"
              },
              {
                "X": 0.0,
                "Y": 0.0,
                "FrameIndex": 21,
                "EasingData": {
                  "Type": 0
                },
                "ctype": "PointFrameData"
              },
              {
                "X": 0.0,
                "Y": 0.0,
                "FrameIndex": 28,
                "EasingData": {
                  "Type": 0
                },
                "ctype": "PointFrameData"
              },
              {
                "X": 0.0,
                "Y": 0.0,
                "FrameIndex": 35,
                "EasingData": {
                  "Type": 0
                },
                "ctype": "PointFrameData"
              },
              {
                "X": 0.0,
                "Y": 0.0,
                "FrameIndex": 80,
                "EasingData": {
                  "Type": 0
                },
                "ctype": "PointFrameData"
              },
              {
                "X": 0.0,
                "Y": 0.0,
                "FrameIndex": 90,
                "EasingData": {
                  "Type": 0
                },
                "ctype": "PointFrameData"
              },
              {
                "X": 0.0,
                "Y": 0.0,
                "FrameIndex": 100,
                "EasingData": {
                  "Type": 0
                },
                "ctype": "PointFrameData"
              }
            ],
            "ctype": "TimelineData"
          },
          {
            "ActionTag": -106618142,
            "Property": "Scale",
            "Frames": [
              {
                "X": 1.0,
                "Y": 1.0,
                "FrameIndex": 0,
                "EasingData": {
                  "Type": 0
                },
                "ctype": "ScaleValueFrameData"
              },
              {
                "X": 1.0,
                "Y": 1.0,
                "FrameIndex": 7,
                "EasingData": {
                  "Type": 0
                },
                "ctype": "ScaleValueFrameData"
              },
              {
                "X": 1.0,
                "Y": 1.0,
                "FrameIndex": 14,
                "EasingData": {
                  "Type": 0
                },
                "ctype": "ScaleValueFrameData"
              },
              {
                "X": 1.0,
                "Y": 1.0,
                "FrameIndex": 21,
                "EasingData": {
                  "Type": 0
                },
                "ctype": "ScaleValueFrameData"
              },
              {
                "X": 1.0,
                "Y": 1.0,
                "FrameIndex": 28,
                "EasingData": {
                  "Type": 0
                },
                "ctype": "ScaleValueFrameData"
              },
              {
                "X": 1.0,
                "Y": 1.0,
                "FrameIndex": 35,
                "EasingData": {
                  "Type": 0
                },
                "ctype": "ScaleValueFrameData"
              },
              {
                "X": 1.0,
                "Y": 1.0,
                "FrameIndex": 80,
                "EasingData": {
                  "Type": 0
                },
                "ctype": "ScaleValueFrameData"
              },
              {
                "X": 1.0,
                "Y": 1.0,
                "FrameIndex": 90,
                "EasingData": {
                  "Type": 0
                },
                "ctype": "ScaleValueFrameData"
              },
              {
                "X": 1.0,
                "Y": 1.0,
                "FrameIndex": 100,
                "EasingData": {
                  "Type": 0
                },
                "ctype": "ScaleValueFrameData"
              }
            ],
            "ctype": "TimelineData"
          },
          {
            "ActionTag": -106618142,
            "Property": "RotationSkew",
            "Frames": [
              {
                "X": 0.0,
                "Y": 0.0,
                "FrameIndex": 0,
                "EasingData": {
                  "Type": 0
                },
                "ctype": "ScaleValueFrameData"
              },
              {
                "X": 0.0,
                "Y": 0.0,
                "FrameIndex": 7,
                "EasingData": {
                  "Type": 0
                },
                "ctype": "ScaleValueFrameData"
              },
              {
                "X": 0.0,
                "Y": 0.0,
                "FrameIndex": 14,
                "EasingData": {
                  "Type": 0
                },
                "ctype": "ScaleValueFrameData"
              },
              {
                "X": 0.0,
                "Y": 0.0,
                "FrameIndex": 21,
                "EasingData": {
                  "Type": 0
                },
                "ctype": "ScaleValueFrameData"
              },
              {
                "X": 0.0,
                "Y": 0.0,
                "FrameIndex": 28,
                "EasingData": {
                  "Type": 0
                },
                "ctype": "ScaleValueFrameData"
              },
              {
                "X": 0.0,
                "Y": 0.0,
                "FrameIndex": 35,
                "EasingData": {
                  "Type": 0
                },
                "ctype": "ScaleValueFrameData"
              },
              {
                "X": 0.0,
                "Y": 0.0,
                "FrameIndex": 80,
                "EasingData": {
                  "Type": 0
                },
                "ctype": "ScaleValueFrameData"
              },
              {
                "X": 0.0,
                "Y": 0.0,
                "FrameIndex": 90,
                "EasingData": {
                  "Type": 0
                },
                "ctype": "ScaleValueFrameData"
              },
              {
                "X": 0.0,
                "Y": 0.0,
                "FrameIndex": 100,
                "EasingData": {
                  "Type": 0
                },
                "ctype": "ScaleValueFrameData"
              }
            ],
            "ctype": "TimelineData"
          },
          {
            "ActionTag": -106618142,
            "Property": "Alpha",
            "Frames": [
              {
                "Value": 0,
                "FrameIndex": 0,
                "EasingData": {
                  "Type": 0
                },
                "ctype": "IntFrameData"
              },
              {
                "Value": 255,
                "FrameIndex": 7,
                "EasingData": {
                  "Type": 0
                },
                "ctype": "IntFrameData"
              },
              {
                "Value": 153,
                "FrameIndex": 14,
                "EasingData": {
                  "Type": 0
                },
                "ctype": "IntFrameData"
              },
              {
                "Value": 255,
                "FrameIndex": 21,
                "EasingData": {
                  "Type": 0
                },
                "ctype": "IntFrameData"
              },
              {
                "Value": 153,
                "FrameIndex": 28,
                "EasingData": {
                  "Type": 0
                },
                "ctype": "IntFrameData"
              },
              {
                "Value": 255,
                "FrameIndex": 35,
                "EasingData": {
                  "Type": 0
                },
                "ctype": "IntFrameData"
              },
              {
                "Value": 255,
                "FrameIndex": 80,
                "EasingData": {
                  "Type": 0
                },
                "ctype": "IntFrameData"
              },
              {
                "Value": 0,
                "FrameIndex": 90,
                "EasingData": {
                  "Type": 0
                },
                "ctype": "IntFrameData"
              },
              {
                "Value": 0,
                "FrameIndex": 100,
                "EasingData": {
                  "Type": 0
                },
                "ctype": "IntFrameData"
              }
            ],
            "ctype": "TimelineData"
          },
          {
            "ActionTag": -779975596,
            "Property": "Position",
            "Frames": [
              {
                "X": 0.0,
                "Y": 0.0,
                "FrameIndex": 34,
                "EasingData": {
                  "Type": 0
                },
                "ctype": "PointFrameData"
              },
              {
                "X": 0.0,
                "Y": 0.0,
                "FrameIndex": 35,
                "EasingData": {
                  "Points": [
                    {
                      "X": 0.0,
                      "Y": 0.0
                    },
                    {
                      "X": 0.0,
                      "Y": 0.79
                    },
                    {
                      "X": 1.0,
                      "Y": 1.0
                    },
                    {
                      "X": 1.0,
                      "Y": 1.0
                    }
                  ],
                  "Type": -1
                },
                "ctype": "PointFrameData"
              },
              {
                "X": 0.0004,
                "Y": 0.0,
                "FrameIndex": 66,
                "EasingData": {
                  "Type": 0
                },
                "ctype": "PointFrameData"
              }
            ],
            "ctype": "TimelineData"
          },
          {
            "ActionTag": -779975596,
            "Property": "Scale",
            "Frames": [
              {
                "X": 1.0,
                "Y": 1.0,
                "FrameIndex": 34,
                "EasingData": {
                  "Type": 0
                },
                "ctype": "ScaleValueFrameData"
              },
              {
                "X": 1.0,
                "Y": 1.0,
                "FrameIndex": 35,
                "EasingData": {
                  "Points": [
                    {
                      "X": 0.0,
                      "Y": 0.0
                    },
                    {
                      "X": 0.0,
                      "Y": 0.79
                    },
                    {
                      "X": 1.0,
                      "Y": 1.0
                    },
                    {
                      "X": 1.0,
                      "Y": 1.0
                    }
                  ],
                  "Type": -1
                },
                "ctype": "ScaleValueFrameData"
              },
              {
                "X": 1.18,
                "Y": 1.35,
                "FrameIndex": 66,
                "EasingData": {
                  "Type": 0
                },
                "ctype": "ScaleValueFrameData"
              }
            ],
            "ctype": "TimelineData"
          },
          {
            "ActionTag": -779975596,
            "Property": "RotationSkew",
            "Frames": [
              {
                "X": 0.0,
                "Y": 0.0,
                "FrameIndex": 34,
                "EasingData": {
                  "Type": 0
                },
                "ctype": "ScaleValueFrameData"
              },
              {
                "X": 0.0,
                "Y": 0.0,
                "FrameIndex": 35,
                "EasingData": {
                  "Points": [
                    {
                      "X": 0.0,
                      "Y": 0.0
                    },
                    {
                      "X": 0.0,
                      "Y": 0.79
                    },
                    {
                      "X": 1.0,
                      "Y": 1.0
                    },
                    {
                      "X": 1.0,
                      "Y": 1.0
                    }
                  ],
                  "Type": -1
                },
                "ctype": "ScaleValueFrameData"
              },
              {
                "X": 0.0,
                "Y": 0.0,
                "FrameIndex": 66,
                "EasingData": {
                  "Type": 0
                },
                "ctype": "ScaleValueFrameData"
              }
            ],
            "ctype": "TimelineData"
          },
          {
            "ActionTag": -779975596,
            "Property": "Alpha",
            "Frames": [
              {
                "Value": 255,
                "FrameIndex": 34,
                "EasingData": {
                  "Type": 0
                },
                "ctype": "IntFrameData"
              },
              {
                "Value": 229,
                "FrameIndex": 35,
                "EasingData": {
                  "Points": [
                    {
                      "X": 0.0,
                      "Y": 0.0
                    },
                    {
                      "X": 0.0,
                      "Y": 0.79
                    },
                    {
                      "X": 1.0,
                      "Y": 1.0
                    },
                    {
                      "X": 1.0,
                      "Y": 1.0
                    }
                  ],
                  "Type": -1
                },
                "ctype": "IntFrameData"
              },
              {
                "Value": 0,
                "FrameIndex": 66,
                "EasingData": {
                  "Type": 0
                },
                "ctype": "IntFrameData"
              }
            ],
            "ctype": "TimelineData"
          },
          {
            "ActionTag": -779975596,
            "Property": "VisibleForFrame",
            "Frames": [
              {
                "Value": false,
                "FrameIndex": 34,
                "Tween": false,
                "ctype": "BoolFrameData"
              },
              {
                "Value": true,
                "FrameIndex": 35,
                "Tween": false,
                "ctype": "BoolFrameData"
              }
            ],
            "ctype": "TimelineData"
          },
          {
            "ActionTag": -779975596,
            "Property": "BlendFunc",
            "Frames": [
              {
                "Src": 770,
                "Dst": 1,
                "FrameIndex": 35,
                "Tween": false,
                "ctype": "BlendFuncFrameData"
              }
            ],
            "ctype": "TimelineData"
          },
          {
            "ActionTag": 1695578559,
            "Property": "Position",
            "Frames": [
              {
                "X": 0.0,
                "Y": 0.0,
                "FrameIndex": 51,
                "EasingData": {
                  "Type": 0
                },
                "ctype": "PointFrameData"
              },
              {
                "X": 0.0,
                "Y": 0.0,
                "FrameIndex": 52,
                "EasingData": {
                  "Points": [
                    {
                      "X": 0.0,
                      "Y": 0.0
                    },
                    {
                      "X": 0.0,
                      "Y": 0.79
                    },
                    {
                      "X": 1.0,
                      "Y": 1.0
                    },
                    {
                      "X": 1.0,
                      "Y": 1.0
                    }
                  ],
                  "Type": -1
                },
                "ctype": "PointFrameData"
              },
              {
                "X": 0.0004,
                "Y": 0.0,
                "FrameIndex": 89,
                "EasingData": {
                  "Type": 0
                },
                "ctype": "PointFrameData"
              }
            ],
            "ctype": "TimelineData"
          },
          {
            "ActionTag": 1695578559,
            "Property": "Scale",
            "Frames": [
              {
                "X": 1.0,
                "Y": 1.0,
                "FrameIndex": 51,
                "EasingData": {
                  "Type": 0
                },
                "ctype": "ScaleValueFrameData"
              },
              {
                "X": 1.0,
                "Y": 1.0,
                "FrameIndex": 52,
                "EasingData": {
                  "Points": [
                    {
                      "X": 0.0,
                      "Y": 0.0
                    },
                    {
                      "X": 0.0,
                      "Y": 0.79
                    },
                    {
                      "X": 1.0,
                      "Y": 1.0
                    },
                    {
                      "X": 1.0,
                      "Y": 1.0
                    }
                  ],
                  "Type": -1
                },
                "ctype": "ScaleValueFrameData"
              },
              {
                "X": 1.18,
                "Y": 1.35,
                "FrameIndex": 89,
                "EasingData": {
                  "Type": 0
                },
                "ctype": "ScaleValueFrameData"
              }
            ],
            "ctype": "TimelineData"
          },
          {
            "ActionTag": 1695578559,
            "Property": "RotationSkew",
            "Frames": [
              {
                "X": 0.0,
                "Y": 0.0,
                "FrameIndex": 51,
                "EasingData": {
                  "Type": 0
                },
                "ctype": "ScaleValueFrameData"
              },
              {
                "X": 0.0,
                "Y": 0.0,
                "FrameIndex": 52,
                "EasingData": {
                  "Points": [
                    {
                      "X": 0.0,
                      "Y": 0.0
                    },
                    {
                      "X": 0.0,
                      "Y": 0.79
                    },
                    {
                      "X": 1.0,
                      "Y": 1.0
                    },
                    {
                      "X": 1.0,
                      "Y": 1.0
                    }
                  ],
                  "Type": -1
                },
                "ctype": "ScaleValueFrameData"
              },
              {
                "X": 0.0,
                "Y": 0.0,
                "FrameIndex": 89,
                "EasingData": {
                  "Type": 0
                },
                "ctype": "ScaleValueFrameData"
              }
            ],
            "ctype": "TimelineData"
          },
          {
            "ActionTag": 1695578559,
            "Property": "Alpha",
            "Frames": [
              {
                "Value": 255,
                "FrameIndex": 51,
                "EasingData": {
                  "Type": 0
                },
                "ctype": "IntFrameData"
              },
              {
                "Value": 204,
                "FrameIndex": 52,
                "EasingData": {
                  "Points": [
                    {
                      "X": 0.0,
                      "Y": 0.0
                    },
                    {
                      "X": 0.0,
                      "Y": 0.79
                    },
                    {
                      "X": 1.0,
                      "Y": 1.0
                    },
                    {
                      "X": 1.0,
                      "Y": 1.0
                    }
                  ],
                  "Type": -1
                },
                "ctype": "IntFrameData"
              },
              {
                "Value": 0,
                "FrameIndex": 89,
                "EasingData": {
                  "Type": 0
                },
                "ctype": "IntFrameData"
              }
            ],
            "ctype": "TimelineData"
          },
          {
            "ActionTag": 1695578559,
            "Property": "VisibleForFrame",
            "Frames": [
              {
                "Value": false,
                "FrameIndex": 51,
                "Tween": false,
                "ctype": "BoolFrameData"
              },
              {
                "Value": true,
                "FrameIndex": 52,
                "Tween": false,
                "ctype": "BoolFrameData"
              }
            ],
            "ctype": "TimelineData"
          },
          {
            "ActionTag": 1695578559,
            "Property": "BlendFunc",
            "Frames": [
              {
                "Src": 770,
                "Dst": 1,
                "FrameIndex": 52,
                "Tween": false,
                "ctype": "BlendFuncFrameData"
              }
            ],
            "ctype": "TimelineData"
          },
          {
            "ActionTag": 2124035947,
            "Property": "Position",
            "Frames": [
              {
                "X": 0.0,
                "Y": 0.0,
                "FrameIndex": 33,
                "EasingData": {
                  "Type": 0
                },
                "ctype": "PointFrameData"
              }
            ],
            "ctype": "TimelineData"
          },
          {
            "ActionTag": 2124035947,
            "Property": "Scale",
            "Frames": [
              {
                "X": 1.0,
                "Y": 1.0,
                "FrameIndex": 33,
                "EasingData": {
                  "Type": 0
                },
                "ctype": "ScaleValueFrameData"
              }
            ],
            "ctype": "TimelineData"
          },
          {
            "ActionTag": 2124035947,
            "Property": "RotationSkew",
            "Frames": [
              {
                "X": 0.0,
                "Y": 0.0,
                "FrameIndex": 33,
                "EasingData": {
                  "Type": 0
                },
                "ctype": "ScaleValueFrameData"
              }
            ],
            "ctype": "TimelineData"
          },
          {
            "ActionTag": 2124035947,
            "Property": "FileData",
            "Frames": [
              {
                "TextureFile": {
                  "Type": "PlistSubImage",
                  "Path": "DN_tx_qiangzhuang_xl101.png",
                  "Plist": "image/ui/animation/DN_tx_qiangzhuang_xl.plist"
                },
                "FrameIndex": 33,
                "Tween": false,
                "ctype": "TextureFrameData"
              },
              {
                "TextureFile": {
                  "Type": "PlistSubImage",
                  "Path": "DN_tx_qiangzhuang_xl101.png",
                  "Plist": "image/ui/animation/DN_tx_qiangzhuang_xl.plist"
                },
                "FrameIndex": 34,
                "Tween": false,
                "ctype": "TextureFrameData"
              },
              {
                "TextureFile": {
                  "Type": "PlistSubImage",
                  "Path": "DN_tx_qiangzhuang_xl102.png",
                  "Plist": "image/ui/animation/DN_tx_qiangzhuang_xl.plist"
                },
                "FrameIndex": 39,
                "Tween": false,
                "ctype": "TextureFrameData"
              },
              {
                "TextureFile": {
                  "Type": "PlistSubImage",
                  "Path": "DN_tx_qiangzhuang_xl103.png",
                  "Plist": "image/ui/animation/DN_tx_qiangzhuang_xl.plist"
                },
                "FrameIndex": 44,
                "Tween": false,
                "ctype": "TextureFrameData"
              },
              {
                "TextureFile": {
                  "Type": "PlistSubImage",
                  "Path": "DN_tx_qiangzhuang_xl104.png",
                  "Plist": "image/ui/animation/DN_tx_qiangzhuang_xl.plist"
                },
                "FrameIndex": 49,
                "Tween": false,
                "ctype": "TextureFrameData"
              },
              {
                "TextureFile": {
                  "Type": "PlistSubImage",
                  "Path": "DN_tx_qiangzhuang_xl101.png",
                  "Plist": "image/ui/animation/DN_tx_qiangzhuang_xl.plist"
                },
                "FrameIndex": 54,
                "Tween": false,
                "ctype": "TextureFrameData"
              },
              {
                "TextureFile": {
                  "Type": "PlistSubImage",
                  "Path": "DN_tx_qiangzhuang_xl102.png",
                  "Plist": "image/ui/animation/DN_tx_qiangzhuang_xl.plist"
                },
                "FrameIndex": 59,
                "Tween": false,
                "ctype": "TextureFrameData"
              },
              {
                "TextureFile": {
                  "Type": "PlistSubImage",
                  "Path": "DN_tx_qiangzhuang_xl103.png",
                  "Plist": "image/ui/animation/DN_tx_qiangzhuang_xl.plist"
                },
                "FrameIndex": 64,
                "Tween": false,
                "ctype": "TextureFrameData"
              },
              {
                "TextureFile": {
                  "Type": "PlistSubImage",
                  "Path": "DN_tx_qiangzhuang_xl104.png",
                  "Plist": "image/ui/animation/DN_tx_qiangzhuang_xl.plist"
                },
                "FrameIndex": 69,
                "Tween": false,
                "ctype": "TextureFrameData"
              },
              {
                "TextureFile": {
                  "Type": "PlistSubImage",
                  "Path": "DN_tx_qiangzhuang_xl101.png",
                  "Plist": "image/ui/animation/DN_tx_qiangzhuang_xl.plist"
                },
                "FrameIndex": 74,
                "Tween": false,
                "ctype": "TextureFrameData"
              },
              {
                "TextureFile": {
                  "Type": "PlistSubImage",
                  "Path": "DN_tx_qiangzhuang_xl102.png",
                  "Plist": "image/ui/animation/DN_tx_qiangzhuang_xl.plist"
                },
                "FrameIndex": 79,
                "Tween": false,
                "ctype": "TextureFrameData"
              },
              {
                "TextureFile": {
                  "Type": "PlistSubImage",
                  "Path": "DN_tx_qiangzhuang_xl103.png",
                  "Plist": "image/ui/animation/DN_tx_qiangzhuang_xl.plist"
                },
                "FrameIndex": 84,
                "Tween": false,
                "ctype": "TextureFrameData"
              },
              {
                "TextureFile": {
                  "Type": "PlistSubImage",
                  "Path": "DN_tx_qiangzhuang_xl104.png",
                  "Plist": "image/ui/animation/DN_tx_qiangzhuang_xl.plist"
                },
                "FrameIndex": 89,
                "Tween": false,
                "ctype": "TextureFrameData"
              }
            ],
            "ctype": "TimelineData"
          },
          {
            "ActionTag": 2124035947,
            "Property": "VisibleForFrame",
            "Frames": [
              {
                "Value": false,
                "FrameIndex": 33,
                "Tween": false,
                "ctype": "BoolFrameData"
              },
              {
                "Value": true,
                "FrameIndex": 34,
                "Tween": false,
                "ctype": "BoolFrameData"
              }
            ],
            "ctype": "TimelineData"
          },
          {
            "ActionTag": -752987995,
            "Property": "Position",
            "Frames": [
              {
                "X": 0.0,
                "Y": 0.0,
                "FrameIndex": 74,
                "EasingData": {
                  "Type": 0
                },
                "ctype": "PointFrameData"
              },
              {
                "X": 0.0,
                "Y": 0.0,
                "FrameIndex": 89,
                "EasingData": {
                  "Type": 0
                },
                "ctype": "PointFrameData"
              }
            ],
            "ctype": "TimelineData"
          },
          {
            "ActionTag": -752987995,
            "Property": "Scale",
            "Frames": [
              {
                "X": 1.0,
                "Y": 1.0,
                "FrameIndex": 74,
                "EasingData": {
                  "Type": 0
                },
                "ctype": "ScaleValueFrameData"
              },
              {
                "X": 1.0,
                "Y": 1.0,
                "FrameIndex": 89,
                "EasingData": {
                  "Type": 0
                },
                "ctype": "ScaleValueFrameData"
              }
            ],
            "ctype": "TimelineData"
          },
          {
            "ActionTag": -752987995,
            "Property": "RotationSkew",
            "Frames": [
              {
                "X": 0.0,
                "Y": 0.0,
                "FrameIndex": 74,
                "EasingData": {
                  "Type": 0
                },
                "ctype": "ScaleValueFrameData"
              },
              {
                "X": 0.0,
                "Y": 0.0,
                "FrameIndex": 89,
                "EasingData": {
                  "Type": 0
                },
                "ctype": "ScaleValueFrameData"
              }
            ],
            "ctype": "TimelineData"
          },
          {
            "ActionTag": -752987995,
            "Property": "Alpha",
            "Frames": [
              {
                "Value": 255,
                "FrameIndex": 74,
                "EasingData": {
                  "Type": 0
                },
                "ctype": "IntFrameData"
              },
              {
                "Value": 0,
                "FrameIndex": 89,
                "EasingData": {
                  "Type": 0
                },
                "ctype": "IntFrameData"
              }
            ],
            "ctype": "TimelineData"
          },
          {
            "ActionTag": -1285980018,
            "Property": "Position",
            "Frames": [
              {
                "X": 0.0,
                "Y": 0.0,
                "FrameIndex": 48,
                "EasingData": {
                  "Type": 0
                },
                "ctype": "PointFrameData"
              },
              {
                "X": 0.0,
                "Y": 0.0,
                "FrameIndex": 49,
                "EasingData": {
                  "Points": [
                    {
                      "X": 0.0,
                      "Y": 0.0
                    },
                    {
                      "X": 0.0,
                      "Y": 0.0
                    },
                    {
                      "X": 1.0,
                      "Y": 0.61
                    },
                    {
                      "X": 1.0,
                      "Y": 1.0
                    }
                  ],
                  "Type": -1
                },
                "ctype": "PointFrameData"
              },
              {
                "X": 0.0,
                "Y": 0.0,
                "FrameIndex": 54,
                "EasingData": {
                  "Type": 0
                },
                "ctype": "PointFrameData"
              },
              {
                "X": 0.0,
                "Y": 0.0,
                "FrameIndex": 63,
                "EasingData": {
                  "Type": 0
                },
                "ctype": "PointFrameData"
              }
            ],
            "ctype": "TimelineData"
          },
          {
            "ActionTag": -1285980018,
            "Property": "Scale",
            "Frames": [
              {
                "X": 1.0,
                "Y": 1.0,
                "FrameIndex": 48,
                "EasingData": {
                  "Type": 0
                },
                "ctype": "ScaleValueFrameData"
              },
              {
                "X": 1.8774,
                "Y": 1.8774,
                "FrameIndex": 49,
                "EasingData": {
                  "Points": [
                    {
                      "X": 0.0,
                      "Y": 0.0
                    },
                    {
                      "X": 0.0,
                      "Y": 0.0
                    },
                    {
                      "X": 1.0,
                      "Y": 0.61
                    },
                    {
                      "X": 1.0,
                      "Y": 1.0
                    }
                  ],
                  "Type": -1
                },
                "ctype": "ScaleValueFrameData"
              },
              {
                "X": 0.7894,
                "Y": 0.7894,
                "FrameIndex": 54,
                "EasingData": {
                  "Type": 0
                },
                "ctype": "ScaleValueFrameData"
              },
              {
                "X": 1.0,
                "Y": 1.0,
                "FrameIndex": 63,
                "EasingData": {
                  "Type": 0
                },
                "ctype": "ScaleValueFrameData"
              }
            ],
            "ctype": "TimelineData"
          },
          {
            "ActionTag": -1285980018,
            "Property": "RotationSkew",
            "Frames": [
              {
                "X": 0.0,
                "Y": 0.0,
                "FrameIndex": 48,
                "EasingData": {
                  "Type": 0
                },
                "ctype": "ScaleValueFrameData"
              },
              {
                "X": 0.0,
                "Y": 0.0,
                "FrameIndex": 49,
                "EasingData": {
                  "Points": [
                    {
                      "X": 0.0,
                      "Y": 0.0
                    },
                    {
                      "X": 0.0,
                      "Y": 0.0
                    },
                    {
                      "X": 1.0,
                      "Y": 0.61
                    },
                    {
                      "X": 1.0,
                      "Y": 1.0
                    }
                  ],
                  "Type": -1
                },
                "ctype": "ScaleValueFrameData"
              },
              {
                "X": 0.0,
                "Y": 0.0,
                "FrameIndex": 54,
                "EasingData": {
                  "Type": 0
                },
                "ctype": "ScaleValueFrameData"
              },
              {
                "X": 0.0,
                "Y": 0.0,
                "FrameIndex": 63,
                "EasingData": {
                  "Type": 0
                },
                "ctype": "ScaleValueFrameData"
              }
            ],
            "ctype": "TimelineData"
          },
          {
            "ActionTag": -1285980018,
            "Property": "VisibleForFrame",
            "Frames": [
              {
                "Value": false,
                "FrameIndex": 48,
                "Tween": false,
                "ctype": "BoolFrameData"
              },
              {
                "Value": true,
                "FrameIndex": 49,
                "Tween": false,
                "ctype": "BoolFrameData"
              },
              {
                "Value": true,
                "FrameIndex": 54,
                "Tween": false,
                "ctype": "BoolFrameData"
              },
              {
                "Value": true,
                "FrameIndex": 63,
                "Tween": false,
                "ctype": "BoolFrameData"
              }
            ],
            "ctype": "TimelineData"
          }
        ],
        "ctype": "TimelineActionData"
      },
      "AnimationList": [
        {
          "StartIndex": 0,
          "EndIndex": 100,
          "Name": "action",
          "ctype": "AnimationInfoData"
        }
      ],
      "ObjectData": {
        "Tag": 3,
        "Children": [
          {
            "AnchorPoint": {},
            "Position": {
              "X": 0.0,
              "Y": 0.0
            },
            "Scale": {
              "ScaleX": 1.0,
              "ScaleY": 1.0
            },
            "CColor": {},
            "IconVisible": true,
            "PrePosition": {
              "X": 0.0,
              "Y": 0.0
            },
            "PreSize": {
              "X": 0.0,
              "Y": 0.0
            },
            "Tag": 8,
            "Children": [
              {
                "FileData": {
                  "Type": "Normal",
                  "Path": "image/ui/animation/DN_qiangzhuang01.png",
                  "Plist": ""
                },
                "BlendFunc": {
                  "Src": 1,
                  "Dst": 771
                },
                "AnchorPoint": {
                  "ScaleX": 0.5,
                  "ScaleY": 0.5
                },
                "Position": {
                  "X": 0.0,
                  "Y": 0.0
                },
                "Scale": {
                  "ScaleX": 1.0,
                  "ScaleY": 1.0
                },
                "CColor": {},
                "IconVisible": false,
                "PrePosition": {
                  "X": 0.0,
                  "Y": 0.0
                },
                "PreSize": {
                  "X": 0.0,
                  "Y": 0.0
                },
                "LeftMargin": -129.0,
                "RightMargin": -129.0,
                "TopMargin": -64.0,
                "BottomMargin": -64.0,
                "Tag": 5,
                "ActionTag": -106618142,
                "Size": {
                  "X": 258.0,
                  "Y": 128.0
                },
                "Name": "xiangkuang3_2",
                "ctype": "SpriteObjectData"
              },
              {
                "AnchorPoint": {},
                "Position": {
                  "X": 0.0,
                  "Y": 0.0
                },
                "Scale": {
                  "ScaleX": 1.0,
                  "ScaleY": 1.0
                },
                "CColor": {},
                "IconVisible": true,
                "PrePosition": {
                  "X": 0.0,
                  "Y": 0.0
                },
                "PreSize": {
                  "X": 0.0,
                  "Y": 0.0
                },
                "Tag": 9,
                "Children": [
                  {
                    "FileData": {
                      "Type": "Normal",
                      "Path": "image/ui/animation/DN_qiangzhuang01.png",
                      "Plist": ""
                    },
                    "BlendFunc": {
                      "Src": 770,
                      "Dst": 1
                    },
                    "AnchorPoint": {
                      "ScaleX": 0.5,
                      "ScaleY": 0.5
                    },
                    "Position": {
                      "X": 0.0004,
                      "Y": 0.0
                    },
                    "Scale": {
                      "ScaleX": 1.18,
                      "ScaleY": 1.35
                    },
                    "CColor": {},
                    "IconVisible": false,
                    "PrePosition": {
                      "X": 0.0,
                      "Y": 0.0
                    },
                    "PreSize": {
                      "X": 0.0,
                      "Y": 0.0
                    },
                    "LeftMargin": -128.9996,
                    "RightMargin": -129.0004,
                    "TopMargin": -64.0,
                    "BottomMargin": -64.0,
                    "Tag": 12,
                    "ActionTag": -779975596,
                    "Size": {
                      "X": 258.0,
                      "Y": 128.0
                    },
                    "Alpha": 0,
                    "Name": "xiangkuang3_2_0_1",
                    "ctype": "SpriteObjectData"
                  },
                  {
                    "FileData": {
                      "Type": "Normal",
                      "Path": "image/ui/animation/DN_qiangzhuang01.png",
                      "Plist": ""
                    },
                    "BlendFunc": {
                      "Src": 770,
                      "Dst": 1
                    },
                    "AnchorPoint": {
                      "ScaleX": 0.5,
                      "ScaleY": 0.5
                    },
                    "Position": {
                      "X": 0.0004,
                      "Y": 0.0
                    },
                    "Scale": {
                      "ScaleX": 1.1602,
                      "ScaleY": 1.3114
                    },
                    "CColor": {},
                    "IconVisible": false,
                    "PrePosition": {
                      "X": 0.0,
                      "Y": 0.0
                    },
                    "PreSize": {
                      "X": 0.0,
                      "Y": 0.0
                    },
                    "LeftMargin": -128.9996,
                    "RightMargin": -129.0004,
                    "TopMargin": -64.0,
                    "BottomMargin": -64.0,
                    "Tag": 11,
                    "ActionTag": 1695578559,
                    "Size": {
                      "X": 258.0,
                      "Y": 128.0
                    },
                    "Alpha": 22,
                    "Name": "xiangkuang3_2_0_0",
                    "ctype": "SpriteObjectData"
                  }
                ],
                "ActionTag": 1165876537,
                "Size": {
                  "X": 0.0,
                  "Y": 0.0
                },
                "Name": "Node_3",
                "ctype": "SingleNodeObjectData"
              },
              {
                "AnchorPoint": {},
                "Position": {
                  "X": 0.0,
                  "Y": 0.0
                },
                "Scale": {
                  "ScaleX": 1.0,
                  "ScaleY": 1.0
                },
                "CColor": {},
                "IconVisible": true,
                "PrePosition": {
                  "X": 0.0,
                  "Y": 0.0
                },
                "PreSize": {
                  "X": 0.0,
                  "Y": 0.0
                },
                "Tag": 6,
                "Children": [
                  {
                    "FileData": {
                      "Type": "PlistSubImage",
                      "Path": "DN_tx_qiangzhuang_xl101.png",
                      "Plist": "image/ui/animation/DN_tx_qiangzhuang_xl.plist"
                    },
                    "BlendFunc": {
                      "Src": 1,
                      "Dst": 771
                    },
                    "AnchorPoint": {
                      "ScaleX": 0.5,
                      "ScaleY": 0.5
                    },
                    "Position": {
                      "X": 0.0,
                      "Y": 0.0
                    },
                    "Scale": {
                      "ScaleX": 1.0,
                      "ScaleY": 1.0
                    },
                    "CColor": {},
                    "IconVisible": false,
                    "PrePosition": {
                      "X": 0.0,
                      "Y": 0.0
                    },
                    "PreSize": {
                      "X": 0.0,
                      "Y": 0.0
                    },
                    "LeftMargin": -136.5,
                    "RightMargin": -136.5,
                    "TopMargin": -71.5,
                    "BottomMargin": -71.5,
                    "Tag": 127,
                    "ActionTag": 2124035947,
                    "Size": {
                      "X": 273.0,
                      "Y": 143.0
                    },
                    "Name": "Sprite_1",
                    "ctype": "SpriteObjectData"
                  }
                ],
                "ActionTag": -752987995,
                "Size": {
                  "X": 0.0,
                  "Y": 0.0
                },
                "Alpha": 238,
                "Name": "Node_1",
                "ctype": "SingleNodeObjectData"
              },
              {
                "AnchorPoint": {},
                "Position": {
                  "X": -105.948,
                  "Y": 48.5203
                },
                "Scale": {
                  "ScaleX": 1.0,
                  "ScaleY": 1.0
                },
                "CColor": {},
                "IconVisible": true,
                "PrePosition": {
                  "X": 0.0,
                  "Y": 0.0
                },
                "PreSize": {
                  "X": 0.0,
                  "Y": 0.0
                },
                "LeftMargin": -105.948,
                "RightMargin": 105.948,
                "TopMargin": -48.5203,
                "BottomMargin": 48.5203,
                "Tag": 151,
                "Children": [
                  {
                    "FileData": {
                      "Type": "Normal",
                      "Path": "image/ui/animation/DN_qiangzhuang03.png",
                      "Plist": ""
                    },
                    "BlendFunc": {
                      "Src": 1,
                      "Dst": 771
                    },
                    "AnchorPoint": {
                      "ScaleX": 0.5,
                      "ScaleY": 0.5
                    },
                    "Position": {
                      "X": 0.0,
                      "Y": 0.0
                    },
                    "Scale": {
                      "ScaleX": 1.0,
                      "ScaleY": 1.0
                    },
                    "CColor": {},
                    "IconVisible": false,
                    "PrePosition": {
                      "X": 0.0,
                      "Y": 0.0
                    },
                    "PreSize": {
                      "X": 0.0,
                      "Y": 0.0
                    },
                    "LeftMargin": -31.5,
                    "RightMargin": -31.5,
                    "TopMargin": -30.5,
                    "BottomMargin": -30.5,
                    "Tag": 150,
                    "ActionTag": -1285980018,
                    "Size": {
                      "X": 63.0,
                      "Y": 61.0
                    },
                    "Name": "DN_qiangzhuang03_1",
                    "ctype": "SpriteObjectData"
                  }
                ],
                "ActionTag": 762250835,
                "Size": {
                  "X": 0.0,
                  "Y": 0.0
                },
                "Name": "Node_3",
                "ctype": "SingleNodeObjectData"
              }
            ],
            "ActionTag": -660905673,
            "Size": {
              "X": 0.0,
              "Y": 0.0
            },
            "Name": "Node_2",
            "ctype": "SingleNodeObjectData"
          }
        ],
        "Size": {
          "X": 0.0,
          "Y": 0.0
        },
        "Name": "Node",
        "ctype": "SingleNodeObjectData"
      },
      "UsedResources": [
        "../image/ui/animation/DN_qiangzhuang01.png",
        "../image/ui/animation/DN_qiangzhuang03.png",
        "../image/ui/animation/DN_tx_qiangzhuang_xl.plist",
        "../image/ui/animation/DN_tx_qiangzhuang_xl.png"
      ],
      "ctype": "GameFileData"
    }
  },
  "Type": "Node"
}